squareofnumber/__init__.py
squareofnumber/square.py
squareofnumber-0.0.2.dist-info/LICENSE
squareofnumber-0.0.2.dist-info/METADATA
squareofnumber-0.0.2.dist-info/WHEEL
squareofnumber-0.0.2.dist-info/top_level.txt
squareofnumber-0.0.2.dist-info/RECORD
